{
  "name": "Гитзерай объединитель / Githzerai Uniter",
  "type": "npc",
  "flags": {
    "core": {}
  },
  "_id": "mjSCqrVYZFiDS9bE",
  "img": "modules/laaru-dnd5-hw/assets/images/pic/Githzerai%20Uniter.webp",
  "system": {
    "abilities": {
      "str": {
        "value": 13,
        "proficient": 1,
        "max": null,
        "bonuses": {
          "check": "",
          "save": "0"
        }
      },
      "dex": {
        "value": 17,
        "proficient": 1,
        "max": null,
        "bonuses": {
          "check": "",
          "save": "0"
        }
      },
      "con": {
        "value": 15,
        "proficient": 0,
        "max": null,
        "bonuses": {
          "check": "",
          "save": "0"
        }
      },
      "int": {
        "value": 15,
        "proficient": 1,
        "max": null,
        "bonuses": {
          "check": "",
          "save": "0"
        }
      },
      "wis": {
        "value": 17,
        "proficient": 1,
        "max": null,
        "bonuses": {
          "check": "",
          "save": "0"
        }
      },
      "cha": {
        "value": 16,
        "proficient": 0,
        "max": null,
        "bonuses": {
          "check": "",
          "save": "0"
        }
      }
    },
    "attributes": {
      "ac": {
        "flat": null,
        "calc": "custom",
        "formula": "@attributes.ac.armor + @attributes.ac.dex +3"
      },
      "hp": {
        "value": 123,
        "max": 123,
        "temp": 0,
        "tempmax": 0,
        "formula": "19d8 + 38"
      },
      "init": {
        "ability": "",
        "bonus": "0",
        "roll": {
          "min": null,
          "max": null,
          "mode": 0
        }
      },
      "movement": {
        "burrow": 0,
        "climb": 0,
        "fly": 0,
        "swim": 0,
        "walk": 40,
        "units": "ft",
        "hover": false
      },
      "attunement": {
        "max": 3
      },
      "senses": {
        "darkvision": 0,
        "blindsight": 0,
        "tremorsense": 0,
        "truesight": 0,
        "units": "ft",
        "special": ""
      },
      "spellcasting": "wis",
      "exhaustion": 0,
      "concentration": {
        "ability": "",
        "roll": {
          "min": null,
          "max": null,
          "mode": 0
        },
        "bonuses": {
          "save": ""
        },
        "limit": 1
      },
      "death": {
        "ability": "",
        "roll": {
          "min": null,
          "max": null,
          "mode": 0
        },
        "success": 0,
        "failure": 0
      },
      "hd": {
        "spent": 0
      }
    },
    "details": {
      "biography": {
        "value": "<p>Гитзераи объединители исповедуют мудрость и единство, а не насилие. Многие объединители являются членами Ша'сал-Хоу, группы гитьянки и гитзераев, объединённых для воссоединения народ гит. Способные мастера боевых искусств, объединители склонны скорее разоружать и усмирять своих противников, нежели уничтожать их.</p><h2 class=\"rd__h rd__h--1\" data-title-index=\"1\">Гитзерай</h2><p>Гитзераи — сосредоточенные философы и строгие аскеты, которые ведут чётко упорядоченную жизнь. Они сухощавые и мускулистые, носят одежду без украшений и орнамента, держат своё мнение при себе и не доверяют практически никому, кроме других гитзераев. Отвернувшись от родственных им, но воинственных гитьянки, гитзераи поддерживают строгий монашеский уклад и обитают на плане Лимб на редких островках порядка в море хаоса.</p><p>Адепты псионики. Предков гитзераев изменила психическая среда, в которую их поместили поработившие иллитиды. Следуя учению Зертимона, который призвал свой народ отвергнуть воинственные амбиции Гит, гитзераи сосредоточили ментальную энергию на создании физических и психических барьеров, защищающих от атак, как обычных, так и психических. Сражение носит личный характер для гитзерая, который с помощью силы разума ошеломляет противников и выводит их из строя, делая уязвимыми к физическим атакам,</p><p>Порядок посреди хаоса. Гитзераи добровольно обитают посреди кромешного хаоса Лимба это вечно меняющийся план, которым гитзераи научились управлять силой своих мощных умов. Лимб это вихрь первородной материи и энергии, местность там представляет собой водоворот камней и земли, который омывают потоки мутной жидкости, обдувают сильные ветра, опаляет огонь и промораживают стены льда.</p><p>Однако силы Лимба реагируют на присутствие сознания. Силой своих умов гитзераи усмирили хаотичные стихии этого плана, зафиксировали их в приемлемых формах и создали оазисы и укрытия посреди вечной бури.</p><p>Крепости-монастыри гитзераев твёрдо стоят посреди окружающего их хаоса, практически неуязвимые для него благодаря силе воли гитзераев. За каждым монастырём надзирают монахи, которые по чёткому расписанию поют гимны, обедают, занимаются боевой подготовкой и совершают обряды согласно своей философии. За укреплёнными стенами гитзераи превыше всего ценят размышления, учение, псионическую силу, порядок и дисциплину.</p><p>Социальная иерархия гитзераев основана на заслугах. Те из них, кто всех мудрее и сильнее в физическом и ментальном бою, становятся лидерами. Гитзераи почитают великих героев и учителей прошлого и в своей ежедневной жизни стремятся следовать их добродетелям.</p><p>Последователи Зертимона. Гитзераи почитают Зертимона, основателя их расы. Хотя свободу им принесла Гит, Зертимон счёл её недостойной власти. Он верил, что из-за воинственного настроя она вскоре станет тираном ничуть не лучше свежевателей разума.</p><p>Умелые монахи гитзераев, лучше других воплощающие учение и принципы Зертимона, называются зертами. Эти сильные и дисциплинированные монахи могут перемещать свои тела с одного плана бытия на другой одной лишь силой мысли.</p><p>За пределами Лимба. Гитзерай редко оказываются за пределами Лимба, но опытные монахи других рас иногда специально ищут монастыри гитзераев и пытаются стать там учениками. Гораздо реже случается так, что учитель из числа гитзераев создаёт на Материальном плане тайный монастырь для обучения молодых гитзераев или распространения философии и учения Зертимона.</p><p>Будучи дисциплинированными, гитзераи всё же не забыли долгого рабства у свежевателей разума. В качестве особого послушания они организуют рраккма - охотничий отряд против иллитидов. Они отправляются на другие планы бытия и не возвращаются в монастыри, пока не убьют как минимум столько иллитидов, сколько охотников входит в отряд.</p>",
        "public": ""
      },
      "alignment": "любое",
      "race": null,
      "type": {
        "value": "aberration",
        "subtype": "гит",
        "swarm": "",
        "custom": ""
      },
      "environment": "",
      "cr": 7,
      "spellLevel": 0,
      "ideal": "",
      "bond": "",
      "flaw": ""
    },
    "traits": {
      "size": "med",
      "di": {
        "value": [],
        "bypasses": [],
        "custom": ""
      },
      "dr": {
        "value": [],
        "bypasses": [],
        "custom": ""
      },
      "dv": {
        "value": [],
        "bypasses": [],
        "custom": ""
      },
      "ci": {
        "value": [],
        "custom": ""
      },
      "languages": {
        "value": [
          "common",
          "gith"
        ],
        "custom": ""
      },
      "dm": {
        "amount": {},
        "bypasses": []
      }
    },
    "currency": {
      "pp": 0,
      "gp": 0,
      "ep": 0,
      "sp": 0,
      "cp": 0
    },
    "skills": {
      "acr": {
        "value": 0,
        "ability": "dex",
        "bonuses": {
          "check": "0",
          "passive": ""
        },
        "roll": {
          "min": null,
          "max": null,
          "mode": 0
        }
      },
      "ani": {
        "value": 0,
        "ability": "wis",
        "bonuses": {
          "check": "0",
          "passive": ""
        },
        "roll": {
          "min": null,
          "max": null,
          "mode": 0
        }
      },
      "arc": {
        "value": 0,
        "ability": "int",
        "bonuses": {
          "check": "0",
          "passive": ""
        },
        "roll": {
          "min": null,
          "max": null,
          "mode": 0
        }
      },
      "ath": {
        "value": 0,
        "ability": "str",
        "bonuses": {
          "check": "0",
          "passive": ""
        },
        "roll": {
          "min": null,
          "max": null,
          "mode": 0
        }
      },
      "dec": {
        "value": 0,
        "ability": "cha",
        "bonuses": {
          "check": "0",
          "passive": ""
        },
        "roll": {
          "min": null,
          "max": null,
          "mode": 0
        }
      },
      "his": {
        "value": 0,
        "ability": "int",
        "bonuses": {
          "check": "0",
          "passive": ""
        },
        "roll": {
          "min": null,
          "max": null,
          "mode": 0
        }
      },
      "ins": {
        "value": 1,
        "ability": "wis",
        "bonuses": {
          "check": "0",
          "passive": ""
        },
        "roll": {
          "min": null,
          "max": null,
          "mode": 0
        }
      },
      "itm": {
        "value": 0,
        "ability": "cha",
        "bonuses": {
          "check": "0",
          "passive": ""
        },
        "roll": {
          "min": null,
          "max": null,
          "mode": 0
        }
      },
      "inv": {
        "value": 0,
        "ability": "int",
        "bonuses": {
          "check": "0",
          "passive": ""
        },
        "roll": {
          "min": null,
          "max": null,
          "mode": 0
        }
      },
      "med": {
        "value": 0,
        "ability": "wis",
        "bonuses": {
          "check": "0",
          "passive": ""
        },
        "roll": {
          "min": null,
          "max": null,
          "mode": 0
        }
      },
      "nat": {
        "value": 0,
        "ability": "int",
        "bonuses": {
          "check": "0",
          "passive": ""
        },
        "roll": {
          "min": null,
          "max": null,
          "mode": 0
        }
      },
      "prc": {
        "value": 1,
        "ability": "wis",
        "bonuses": {
          "check": "0",
          "passive": ""
        },
        "roll": {
          "min": null,
          "max": null,
          "mode": 0
        }
      },
      "prf": {
        "value": 0,
        "ability": "cha",
        "bonuses": {
          "check": "0",
          "passive": ""
        },
        "roll": {
          "min": null,
          "max": null,
          "mode": 0
        }
      },
      "per": {
        "value": 0,
        "ability": "cha",
        "bonuses": {
          "check": "0",
          "passive": ""
        },
        "roll": {
          "min": null,
          "max": null,
          "mode": 0
        }
      },
      "rel": {
        "value": 0,
        "ability": "int",
        "bonuses": {
          "check": "0",
          "passive": ""
        },
        "roll": {
          "min": null,
          "max": null,
          "mode": 0
        }
      },
      "slt": {
        "value": 0,
        "ability": "dex",
        "bonuses": {
          "check": "0",
          "passive": ""
        },
        "roll": {
          "min": null,
          "max": null,
          "mode": 0
        }
      },
      "ste": {
        "value": 0,
        "ability": "dex",
        "bonuses": {
          "check": "0",
          "passive": ""
        },
        "roll": {
          "min": null,
          "max": null,
          "mode": 0
        }
      },
      "sur": {
        "value": 0,
        "ability": "wis",
        "bonuses": {
          "check": "0",
          "passive": ""
        },
        "roll": {
          "min": null,
          "max": null,
          "mode": 0
        }
      }
    },
    "tools": {},
    "spells": {
      "spell1": {
        "value": 0,
        "override": null
      },
      "spell2": {
        "value": 0,
        "override": null
      },
      "spell3": {
        "value": 0,
        "override": null
      },
      "spell4": {
        "value": 0,
        "override": null
      },
      "spell5": {
        "value": 0,
        "override": null
      },
      "spell6": {
        "value": 0,
        "override": null
      },
      "spell7": {
        "value": 0,
        "override": null
      },
      "spell8": {
        "value": 0,
        "override": null
      },
      "spell9": {
        "value": 0,
        "override": null
      },
      "pact": {
        "value": 0,
        "override": null
      },
      "spell0": {
        "value": 0,
        "override": null
      }
    },
    "bonuses": {
      "mwak": {
        "attack": "",
        "damage": ""
      },
      "rwak": {
        "attack": "",
        "damage": ""
      },
      "msak": {
        "attack": "",
        "damage": ""
      },
      "rsak": {
        "attack": "",
        "damage": ""
      },
      "abilities": {
        "check": "",
        "save": "",
        "skill": ""
      },
      "spell": {
        "dc": ""
      }
    },
    "resources": {
      "legact": {
        "value": 0,
        "max": 0
      },
      "legres": {
        "value": 0,
        "max": 0
      },
      "lair": {
        "value": false,
        "initiative": 20
      }
    },
    "source": {
      "page": "",
      "license": "",
      "rules": "2014",
      "book": "MPP"
    }
  },
  "prototypeToken": {
    "name": "Гитзерай объединитель",
    "displayName": 20,
    "actorLink": false,
    "texture": {
      "src": "modules/laaru-dnd5-hw/assets/images/MM/Githzerai Uniter.webp",
      "scaleX": 1,
      "scaleY": 1,
      "offsetX": 0,
      "offsetY": 0,
      "rotation": 0,
      "tint": "#ffffff",
      "anchorX": 0.5,
      "anchorY": 0.5,
      "fit": "contain",
      "alphaThreshold": 0.75
    },
    "width": 1,
    "height": 1,
    "lockRotation": false,
    "rotation": 0,
    "alpha": 1,
    "disposition": -1,
    "displayBars": 40,
    "bar1": {
      "attribute": "attributes.hp"
    },
    "bar2": {
      "attribute": null
    },
    "light": {
      "alpha": 0.5,
      "angle": 360,
      "bright": 0,
      "color": null,
      "coloration": 1,
      "dim": 0,
      "attenuation": 0.5,
      "luminosity": 0.5,
      "saturation": 0,
      "contrast": 0,
      "shadows": 0,
      "animation": {
        "type": null,
        "speed": 5,
        "intensity": 5,
        "reverse": false
      },
      "darkness": {
        "min": 0,
        "max": 1
      },
      "negative": false,
      "priority": 0
    },
    "sight": {
      "enabled": true,
      "range": 0,
      "angle": 360,
      "visionMode": "basic",
      "color": null,
      "attenuation": 0.1,
      "brightness": 1,
      "saturation": 0,
      "contrast": 0
    },
    "detectionModes": [],
    "flags": {},
    "randomImg": false,
    "appendNumber": false,
    "prependAdjective": false,
    "hexagonalShape": 0,
    "occludable": {
      "radius": 0
    },
    "ring": {
      "enabled": false,
      "colors": {
        "ring": null,
        "background": null
      },
      "effects": 1,
      "subject": {
        "scale": 1,
        "texture": null
      }
    }
  },
  "items": [
    {
      "name": "Мультиатака",
      "type": "feat",
      "system": {
        "description": {
          "value": "<p>Гитзерай совершает три атаки Безоружным ударом или Псионическим снарядом. Он может заменить любую из этих атак одним использованием Умиротворяющего прикосновения.</p>",
          "chat": "<p>У существа есть мультиатака.</p>"
        },
        "source": {
          "custom": "MPP",
          "book": "",
          "page": "",
          "license": "",
          "revision": 1,
          "rules": "2014"
        },
        "uses": {
          "max": "",
          "spent": 0,
          "recovery": []
        },
        "type": {
          "value": "",
          "subtype": ""
        },
        "requirements": "",
        "properties": [],
        "activities": {
          "dnd5eactivity000": {
            "_id": "dnd5eactivity000",
            "type": "utility",
            "activation": {
              "type": "action",
              "value": 1,
              "condition": "",
              "override": false
            },
            "consumption": {
              "targets": [],
              "scaling": {
                "allowed": false,
                "max": ""
              },
              "spellSlot": true
            },
            "description": {
              "chatFlavor": ""
            },
            "duration": {
              "concentration": false,
              "value": "",
              "units": "",
              "special": "",
              "override": false
            },
            "effects": [],
            "range": {
              "units": "",
              "special": "",
              "override": false
            },
            "target": {
              "template": {
                "count": "",
                "contiguous": false,
                "type": "",
                "size": "",
                "width": "",
                "height": "",
                "units": ""
              },
              "affects": {
                "count": "",
                "type": "",
                "choice": false,
                "special": ""
              },
              "prompt": true,
              "override": false
            },
            "uses": {
              "spent": 0,
              "max": "",
              "recovery": []
            },
            "roll": {
              "formula": "",
              "name": "",
              "prompt": false,
              "visible": false
            },
            "sort": 0
          }
        },
        "identifier": "",
        "enchant": {},
        "prerequisites": {
          "level": null
        }
      },
      "ownership": {
        "default": 0,
        "ZbpZyP5KRR8A9JvZ": 3
      },
      "img": "icons/skills/melee/strike-weapons-orange.webp",
      "flags": {
        "core": {
          "sourceId": "Actor.mjSCqrVYZFiDS9bE.Item.U9tE3a2m7VFOvk6X"
        },
        "dnd5e": {
          "persistSourceMigration": true
        }
      },
      "effects": [],
      "_id": "U9tE3a2m7VFOvk6X",
      "folder": null,
      "sort": 0,
      "_stats": {
        "compendiumSource": "Actor.mjSCqrVYZFiDS9bE.Item.U9tE3a2m7VFOvk6X",
        "duplicateSource": null,
        "coreVersion": "12.331",
        "systemId": "dnd5e",
        "systemVersion": "4.0.1",
        "createdTime": null,
        "modifiedTime": null,
        "lastModifiedBy": null
      },
      "_key": "!actors.items!mjSCqrVYZFiDS9bE.U9tE3a2m7VFOvk6X"
    },
    {
      "system": {
        "description": {
          "value": "<p><i>Атака оружием в ближнем бою:</i> [[/r 1d20+6]]{+6} к броску, зона досягаемости 5 футов, одна цель. </p><p><i>Попадание:</i> 7 ([[/r 1d8 + 3]]) дробящего урона плюс 10 ([[/r 3d6]]) психического урона.</p>",
          "chat": "<p>Существо бьёт с размаху!</p>"
        },
        "source": {
          "custom": "MPP",
          "book": "",
          "page": "",
          "license": "",
          "revision": 1,
          "rules": "2014"
        },
        "quantity": 1,
        "weight": {
          "value": 0,
          "units": "lb"
        },
        "price": {
          "value": 0,
          "denomination": "gp"
        },
        "attunement": "",
        "equipped": true,
        "rarity": "",
        "identified": true,
        "cover": null,
        "crewed": false,
        "range": {
          "value": 5,
          "long": null,
          "units": "ft",
          "reach": null
        },
        "uses": {
          "max": "",
          "spent": 0,
          "recovery": []
        },
        "damage": {
          "versatile": {
            "number": null,
            "denomination": null,
            "bonus": "",
            "types": [],
            "custom": {
              "enabled": false,
              "formula": ""
            },
            "scaling": {
              "mode": "",
              "number": null,
              "formula": ""
            }
          },
          "base": {
            "number": 1,
            "denomination": 8,
            "bonus": "",
            "types": [
              "bludgeoning"
            ],
            "custom": {
              "enabled": false,
              "formula": ""
            },
            "scaling": {
              "mode": "",
              "number": null,
              "formula": ""
            }
          }
        },
        "armor": {
          "value": null
        },
        "hp": {
          "value": null,
          "max": null,
          "dt": null,
          "conditions": ""
        },
        "properties": [],
        "proficient": 1,
        "unidentified": {
          "description": ""
        },
        "type": {
          "value": "natural",
          "baseItem": ""
        },
        "container": null,
        "magicalBonus": null,
        "activities": {
          "dnd5eactivity000": {
            "_id": "dnd5eactivity000",
            "type": "attack",
            "activation": {
              "type": "action",
              "value": 1,
              "condition": "",
              "override": false
            },
            "consumption": {
              "targets": [],
              "scaling": {
                "allowed": false,
                "max": ""
              },
              "spellSlot": true
            },
            "description": {
              "chatFlavor": ""
            },
            "duration": {
              "concentration": false,
              "value": "",
              "units": "",
              "special": "",
              "override": false
            },
            "effects": [],
            "range": {
              "value": "5",
              "units": "ft",
              "special": "",
              "override": false
            },
            "target": {
              "template": {
                "count": "",
                "contiguous": false,
                "type": "",
                "size": "",
                "width": "",
                "height": "",
                "units": ""
              },
              "affects": {
                "count": "",
                "type": "",
                "choice": false,
                "special": ""
              },
              "prompt": true,
              "override": false
            },
            "uses": {
              "spent": 0,
              "max": "",
              "recovery": []
            },
            "attack": {
              "ability": "dex",
              "bonus": "",
              "critical": {
                "threshold": null
              },
              "flat": false,
              "type": {
                "value": "melee",
                "classification": "weapon"
              }
            },
            "damage": {
              "critical": {
                "bonus": ""
              },
              "includeBase": true,
              "parts": []
            },
            "sort": 0
          }
        },
        "identifier": "",
        "attuned": false,
        "ammunition": {}
      },
      "name": "Безоружный удар",
      "type": "weapon",
      "ownership": {
        "default": 0,
        "ZbpZyP5KRR8A9JvZ": 3
      },
      "img": "icons/equipment/hand/gauntlet-simple-leather-brown-gold.webp",
      "flags": {
        "core": {
          "sourceId": "Actor.mjSCqrVYZFiDS9bE.Item.KFjJYh3bNBhNfHgA"
        },
        "dnd5e": {
          "persistSourceMigration": true
        }
      },
      "effects": [],
      "_id": "KFjJYh3bNBhNfHgA",
      "folder": null,
      "sort": 0,
      "_stats": {
        "compendiumSource": "Actor.mjSCqrVYZFiDS9bE.Item.KFjJYh3bNBhNfHgA",
        "duplicateSource": null,
        "coreVersion": "12.331",
        "systemId": "dnd5e",
        "systemVersion": "4.0.1",
        "createdTime": null,
        "modifiedTime": null,
        "lastModifiedBy": null
      },
      "_key": "!actors.items!mjSCqrVYZFiDS9bE.KFjJYh3bNBhNfHgA"
    },
    {
      "system": {
        "description": {
          "value": "<p><i>Дистанционная атака заклинанием:</i> [[/r 1d20+6]]{+6} к броску, дистанция 60 футов, one creature. </p><p><i>Попадание:</i> 17 ([[/r 5d6]]) психического урона.</p>",
          "chat": "<p>Атака заклинанием!</p>"
        },
        "source": {
          "custom": "MPP",
          "book": "",
          "page": "",
          "license": "",
          "revision": 1,
          "rules": "2014"
        },
        "quantity": 1,
        "weight": {
          "value": 0,
          "units": "lb"
        },
        "price": {
          "value": 0,
          "denomination": "gp"
        },
        "attunement": "",
        "equipped": true,
        "rarity": "",
        "identified": true,
        "cover": null,
        "crewed": false,
        "range": {
          "value": 60,
          "long": null,
          "units": "ft",
          "reach": null
        },
        "uses": {
          "max": "",
          "spent": 0,
          "recovery": []
        },
        "damage": {
          "versatile": {
            "number": null,
            "denomination": null,
            "bonus": "",
            "types": [],
            "custom": {
              "enabled": false,
              "formula": ""
            },
            "scaling": {
              "mode": "",
              "number": null,
              "formula": ""
            }
          },
          "base": {
            "number": 5,
            "denomination": 6,
            "bonus": "",
            "types": [
              "psychic"
            ],
            "custom": {
              "enabled": false,
              "formula": ""
            },
            "scaling": {
              "mode": "",
              "number": null,
              "formula": ""
            }
          }
        },
        "armor": {
          "value": null
        },
        "hp": {
          "value": null,
          "max": null,
          "dt": null,
          "conditions": ""
        },
        "properties": [],
        "proficient": 1,
        "unidentified": {
          "description": ""
        },
        "type": {
          "value": "natural",
          "baseItem": ""
        },
        "container": null,
        "magicalBonus": null,
        "activities": {
          "dnd5eactivity000": {
            "_id": "dnd5eactivity000",
            "type": "attack",
            "activation": {
              "type": "action",
              "value": 1,
              "condition": "",
              "override": false
            },
            "consumption": {
              "targets": [],
              "scaling": {
                "allowed": false,
                "max": ""
              },
              "spellSlot": true
            },
            "description": {
              "chatFlavor": ""
            },
            "duration": {
              "concentration": false,
              "value": "",
              "units": "",
              "special": "",
              "override": false
            },
            "effects": [],
            "range": {
              "value": "60",
              "units": "ft",
              "special": "",
              "override": false
            },
            "target": {
              "template": {
                "count": "",
                "contiguous": false,
                "type": "",
                "size": "",
                "width": "",
                "height": "",
                "units": ""
              },
              "affects": {
                "count": "",
                "type": "",
                "choice": false,
                "special": ""
              },
              "prompt": true,
              "override": false
            },
            "uses": {
              "spent": 0,
              "max": "",
              "recovery": []
            },
            "attack": {
              "ability": "dex",
              "bonus": "",
              "critical": {
                "threshold": null
              },
              "flat": false,
              "type": {
                "value": "ranged",
                "classification": "spell"
              }
            },
            "damage": {
              "critical": {
                "bonus": ""
              },
              "includeBase": true,
              "parts": []
            },
            "sort": 0
          }
        },
        "identifier": "",
        "attuned": false,
        "ammunition": {}
      },
      "name": "Псионический снаряд",
      "type": "weapon",
      "ownership": {
        "default": 0,
        "ZbpZyP5KRR8A9JvZ": 3
      },
      "img": "icons/magic/light/projectile-smoke-yellow.webp",
      "flags": {
        "core": {
          "sourceId": "Actor.mjSCqrVYZFiDS9bE.Item.gq6rymm2GOy4nQcl"
        },
        "dnd5e": {
          "persistSourceMigration": true
        }
      },
      "effects": [],
      "_id": "gq6rymm2GOy4nQcl",
      "folder": null,
      "sort": 0,
      "_stats": {
        "compendiumSource": "Actor.mjSCqrVYZFiDS9bE.Item.gq6rymm2GOy4nQcl",
        "duplicateSource": null,
        "coreVersion": "12.331",
        "systemId": "dnd5e",
        "systemVersion": "4.0.1",
        "createdTime": null,
        "modifiedTime": null,
        "lastModifiedBy": null
      },
      "_key": "!actors.items!mjSCqrVYZFiDS9bE.gq6rymm2GOy4nQcl"
    },
    {
      "name": "Умиротворяющее прикосновение",
      "type": "feat",
      "system": {
        "description": {
          "value": "<p>Гитзерай прикасается к одному существу, которое он может видеть в пределах 5 футов. Цель должна преуспеть в испытании Интеллекта со СЛ 14, иначе гитзерай выбирает действие этой цели: @UUID[Compendium.laaru-dnd5-hw.actions.Y0O7jQKh7vGMSTBu]{Атака}, @UUID[Compendium.laaru-dnd5-hw.actions.6J7Gfe3Hzi6ySFRJ]{Сотворение заклинания} или @Compendium[laaru-dnd5-hw.actions.v1tkJ8DKVJFCNFPM]{Рывок}. Пораженная цель не может совершать это действие в течение 1 минуты. В конце каждого своего хода она может повторять испытание, заканчивая действие этого эффекта в случае успеха. Цель, преуспевшая в испытании, становится невосприимчивой к Умиротворяющему прикосновению этого гитзерая на 24 часа.</p>",
          "chat": "<p>Гитзерай прикасается к одному существу, которое он может видеть в пределах 5 футов. Цель должна преуспеть в испытании Интеллекта.</p>"
        },
        "source": {
          "custom": "MPP",
          "book": "",
          "page": "",
          "license": "",
          "revision": 1,
          "rules": "2014"
        },
        "uses": {
          "max": "",
          "spent": 0,
          "recovery": []
        },
        "type": {
          "value": "",
          "subtype": ""
        },
        "requirements": "",
        "properties": [],
        "activities": {
          "dnd5eactivity000": {
            "_id": "dnd5eactivity000",
            "type": "save",
            "activation": {
              "type": "action",
              "value": 1,
              "condition": "",
              "override": false
            },
            "consumption": {
              "targets": [],
              "scaling": {
                "allowed": false,
                "max": ""
              },
              "spellSlot": true
            },
            "description": {
              "chatFlavor": ""
            },
            "duration": {
              "concentration": false,
              "value": "",
              "units": "",
              "special": "",
              "override": false
            },
            "effects": [],
            "range": {
              "units": "",
              "special": "",
              "override": false
            },
            "target": {
              "template": {
                "count": "",
                "contiguous": false,
                "type": "",
                "size": "",
                "width": "",
                "height": "",
                "units": ""
              },
              "affects": {
                "count": "",
                "type": "",
                "choice": false,
                "special": ""
              },
              "prompt": true,
              "override": false
            },
            "uses": {
              "spent": 0,
              "max": "",
              "recovery": []
            },
            "damage": {
              "onSave": "half",
              "parts": []
            },
            "save": {
              "ability": "int",
              "dc": {
                "calculation": "wis",
                "formula": "14"
              }
            },
            "sort": 0
          }
        },
        "identifier": "",
        "enchant": {},
        "prerequisites": {
          "level": null
        }
      },
      "ownership": {
        "default": 0,
        "ZbpZyP5KRR8A9JvZ": 3
      },
      "img": "icons/magic/death/hand-withered-gray.webp",
      "flags": {
        "core": {
          "sourceId": "Actor.mjSCqrVYZFiDS9bE.Item.EMLOODCophDDVpB3"
        },
        "dnd5e": {
          "persistSourceMigration": true
        }
      },
      "effects": [],
      "_id": "EMLOODCophDDVpB3",
      "folder": null,
      "sort": 0,
      "_stats": {
        "compendiumSource": "Actor.mjSCqrVYZFiDS9bE.Item.EMLOODCophDDVpB3",
        "duplicateSource": null,
        "coreVersion": "12.331",
        "systemId": "dnd5e",
        "systemVersion": "4.0.1",
        "createdTime": null,
        "modifiedTime": null,
        "lastModifiedBy": null
      },
      "_key": "!actors.items!mjSCqrVYZFiDS9bE.EMLOODCophDDVpB3"
    },
    {
      "name": "Планарный переход",
      "type": "spell",
      "system": {
        "description": {
          "value": "<p>Вы и не более восьми согласных существ, сцепивших руки в круг, переноситесь на другой план бытия. Вы можете указать место перемещения в общих чертах, например Латунный город на Стихийном плане Огня или дворец Дисплатера на втором круге Девяти Преисподних, и вы окажетесь в указанном месте. Если, к примеру, вы пытаетесь попасть в Латунный город, то по усмотрению мастера вы можете попасть на Стальную улицу, к Пепельным вратам, а можете и оказаться напротив него по другую сторону узкого пролива в Море Огня.</p>\n<p>Как вариант, если вы знаете последовательность символов круга телепортации на другом плане бытия, заклинание может перенести вас в этот круг. Если размеров круга телепортации недостаточно, чтобы вместить всех перенесённых вами существ, они появятся в ближайшем незанятом пространстве рядом с кругом.</p>\n<p>Вы можете применить это заклинание, чтобы изгнать несогласное существо на другой план. Выберите существо в пределах вашей зоны досягаемости и совершите по нему атаку заклинанием в ближнем бою. При попадании существо должно пройти испытание Харизмы. При провале оно перемещается в случайно выбранное место на указанном вами плане бытия. Существо, перенесённое таким образом, должно само найти, как вернуться на ваш план.</p>",
          "chat": ""
        },
        "source": {
          "custom": "PHB",
          "book": "",
          "page": "",
          "license": "",
          "revision": 1,
          "rules": "2014"
        },
        "activation": {
          "type": "action",
          "condition": "",
          "value": 1
        },
        "duration": {
          "value": "",
          "units": "inst"
        },
        "target": {
          "affects": {
            "type": "creature",
            "count": "8",
            "choice": false
          },
          "template": {
            "units": "touch",
            "contiguous": false
          }
        },
        "range": {
          "value": "0",
          "units": "touch"
        },
        "uses": {
          "max": "1",
          "recovery": [
            {
              "period": "day",
              "type": "recoverAll"
            }
          ],
          "spent": 0
        },
        "ability": "wis",
        "level": 7,
        "school": "con",
        "materials": {
          "value": "раздвоенный металлический стержень стоимостью не менее 250 зм, настроенный на определённый план бытия",
          "consumed": false,
          "cost": 250,
          "supply": 0
        },
        "preparation": {
          "mode": "innate",
          "prepared": true
        },
        "properties": [
          "vocal",
          "somatic",
          "material"
        ],
        "activities": {
          "dnd5eactivity000": {
            "_id": "dnd5eactivity000",
            "type": "attack",
            "activation": {
              "type": "action",
              "value": null,
              "override": false
            },
            "consumption": {
              "targets": [
                {
                  "type": "itemUses",
                  "target": "",
                  "value": "1",
                  "scaling": {
                    "mode": "",
                    "formula": ""
                  }
                }
              ],
              "scaling": {
                "allowed": false,
                "max": ""
              },
              "spellSlot": true
            },
            "description": {
              "chatFlavor": ""
            },
            "duration": {
              "units": "inst",
              "concentration": false,
              "override": false
            },
            "effects": [],
            "range": {
              "override": false
            },
            "target": {
              "prompt": true,
              "template": {
                "contiguous": false,
                "units": "ft"
              },
              "affects": {
                "choice": false
              },
              "override": false
            },
            "uses": {
              "spent": 0,
              "max": "",
              "recovery": []
            },
            "attack": {
              "ability": "wis",
              "bonus": "",
              "critical": {
                "threshold": null
              },
              "flat": false,
              "type": {
                "value": "melee",
                "classification": "spell"
              }
            },
            "damage": {
              "critical": {
                "bonus": ""
              },
              "includeBase": true,
              "parts": []
            },
            "sort": 0
          },
          "dnd5eactivity100": {
            "_id": "dnd5eactivity100",
            "type": "save",
            "activation": {
              "type": "action",
              "value": null,
              "override": false
            },
            "consumption": {
              "targets": [
                {
                  "type": "itemUses",
                  "target": "",
                  "value": "1",
                  "scaling": {
                    "mode": "",
                    "formula": ""
                  }
                }
              ],
              "scaling": {
                "allowed": false,
                "max": ""
              },
              "spellSlot": true
            },
            "description": {
              "chatFlavor": ""
            },
            "duration": {
              "units": "inst",
              "concentration": false,
              "override": false
            },
            "effects": [],
            "range": {
              "override": false
            },
            "target": {
              "prompt": true,
              "template": {
                "contiguous": false,
                "units": "ft"
              },
              "affects": {
                "choice": false
              },
              "override": false
            },
            "uses": {
              "spent": 0,
              "max": "",
              "recovery": []
            },
            "damage": {
              "onSave": "half",
              "parts": []
            },
            "save": {
              "ability": "cha",
              "dc": {
                "calculation": "wis",
                "formula": ""
              }
            },
            "sort": 0
          }
        },
        "identifier": ""
      },
      "img": "icons/tools/navigation/sextant-complex-brown.webp",
      "ownership": {
        "default": 0,
        "ZbpZyP5KRR8A9JvZ": 3
      },
      "flags": {
        "dnd5e": {
          "migratedProperties": [
            "vocal",
            "somatic",
            "material"
          ],
          "persistSourceMigration": true,
          "migratedUses": 1
        }
      },
      "effects": [],
      "_id": "gQDOlECAwUt2bmtg",
      "folder": null,
      "sort": 0,
      "_stats": {
        "compendiumSource": null,
        "duplicateSource": null,
        "coreVersion": "12.331",
        "systemId": "dnd5e",
        "systemVersion": "4.0.1",
        "createdTime": null,
        "modifiedTime": null,
        "lastModifiedBy": null
      },
      "_key": "!actors.items!mjSCqrVYZFiDS9bE.gQDOlECAwUt2bmtg"
    },
    {
      "name": "Телекинез",
      "type": "spell",
      "system": {
        "description": {
          "value": "<p>Вы получаете способность силой мысли перемещать существ или объекты и манипулировать ими. Когда вы сотворяете это заклинание и в качестве действия в каждый раунд, пока оно длится, вы можете управлять силой мысли одним существом или объектом, который вы видите в пределах дистанции, создавая один из перечисленных далее эффектов. Вы можете воздействовать на одну и ту же цель в каждом раунде, а можете каждый раз выбирать новую. Если вы поменяете цель, заклинание прекращает влиять на предыдущую.</p><ul><li><p><strong>Существо.</strong> Вы можете переместить существо огромного размера или меньше. Пройдите проверку вашей заклинательной характеристики в состязании с проверкой Силы существа. Если вы выиграли, можете переместить существо на расстояние до 30 футов в любом направлении, в том числе вверх, но не за пределы дистанции заклинания. До конца вашего следующего хода существо &amp;reference[restrained]{обездвижено} вашим телекинетическим захватом. Существо, поднятое вверх, останется подвешенным в воздухе.</p><p>В последующие раунды вы можете использовать действие, чтобы попытаться поддержать ваш телекинетический захват на существе, повторяя это состязание.</p></li><li><p><strong>Объект. </strong>Вы можете переместить объект, весящий не более 1 000 фунтов. Если это не предмет, который носят или держат, переместите его на расстояние до 30 футов в любом направлении, но не за пределы дистанции заклинания.</p><p>Если это предмет, который носит или держит существо, пройдите проверку вашей заклинательной характеристики в состязании с проверкой Силы существа. При успехе можете забрать предмет у существа и переместить его на расстояние до 30 футов в любом направлении, но не за пределы дистанции заклинания.</p></li></ul><p>Вы можете в точности контролировать движения предметов телекинетическим захватом: орудовать простыми инструментами, открывать двери и контейнеры, доставать из контейнеров предметы и убирать их, выливать содержимое пузырьков.</p>",
          "chat": ""
        },
        "source": {
          "custom": "PHB",
          "book": "",
          "page": "",
          "license": "",
          "revision": 1,
          "rules": "2014"
        },
        "activation": {
          "type": "action",
          "condition": "",
          "value": 1
        },
        "duration": {
          "value": "10",
          "units": "minute"
        },
        "target": {
          "affects": {
            "type": "creature",
            "count": "1",
            "choice": false
          },
          "template": {
            "units": "",
            "contiguous": false
          }
        },
        "range": {
          "value": "60",
          "units": "ft"
        },
        "uses": {
          "max": "1",
          "recovery": [
            {
              "period": "day",
              "type": "recoverAll"
            }
          ],
          "spent": 0
        },
        "ability": "wis",
        "level": 5,
        "school": "trs",
        "materials": {
          "value": "",
          "consumed": false,
          "cost": 0,
          "supply": 0
        },
        "preparation": {
          "mode": "innate",
          "prepared": true
        },
        "properties": [
          "vocal",
          "somatic",
          "concentration"
        ],
        "activities": {
          "dnd5eactivity000": {
            "_id": "dnd5eactivity000",
            "type": "utility",
            "activation": {
              "type": "action",
              "value": null,
              "override": false
            },
            "consumption": {
              "targets": [
                {
                  "type": "itemUses",
                  "target": "",
                  "value": "1",
                  "scaling": {
                    "mode": "",
                    "formula": ""
                  }
                }
              ],
              "scaling": {
                "allowed": false,
                "max": ""
              },
              "spellSlot": true
            },
            "description": {
              "chatFlavor": ""
            },
            "duration": {
              "units": "inst",
              "concentration": false,
              "override": false
            },
            "effects": [],
            "range": {
              "override": false
            },
            "target": {
              "prompt": true,
              "template": {
                "contiguous": false,
                "units": "ft"
              },
              "affects": {
                "choice": false
              },
              "override": false
            },
            "uses": {
              "spent": 0,
              "max": "",
              "recovery": []
            },
            "roll": {
              "formula": "",
              "name": "",
              "prompt": false,
              "visible": false
            },
            "sort": 0
          }
        },
        "identifier": ""
      },
      "img": "icons/skills/toxins/cup-goblet-poisoned-spilled.webp",
      "ownership": {
        "default": 0,
        "ZbpZyP5KRR8A9JvZ": 3
      },
      "flags": {
        "dnd5e": {
          "migratedProperties": [
            "vocal",
            "somatic",
            "concentration"
          ],
          "persistSourceMigration": true,
          "migratedUses": 1
        }
      },
      "effects": [],
      "_id": "GgULV8Nkx736fH8F",
      "folder": null,
      "sort": 0,
      "_stats": {
        "compendiumSource": null,
        "duplicateSource": null,
        "coreVersion": "12.331",
        "systemId": "dnd5e",
        "systemVersion": "4.0.1",
        "createdTime": null,
        "modifiedTime": null,
        "lastModifiedBy": null
      },
      "_key": "!actors.items!mjSCqrVYZFiDS9bE.GgULV8Nkx736fH8F"
    },
    {
      "name": "Магическая рука",
      "type": "spell",
      "system": {
        "description": {
          "value": "<p>Призрачная рука появляется в воздухе в выбранной вами точке в пределах дистанции. Она существует до окончания длительности или пока вы не прекратите заклинание, потратив действие. Рука исчезает, если окажется более чем в 30 футах от вас или если вы снова сотворите это заклинание. Вы можете использовать действие, чтобы управлять рукой. С её помощью вы можете манипулировать предметами, открыть незапертую дверь или контейнер, убрать или достать предмет из открытого контейнера или выплеснуть содержимое пузырька. Вы можете перемещать руку на расстояние до 30 футов каждый раз, когда используете её. Рука не может атаковать, активировать магические предметы и поднимать более 10 фунтов.</p>",
          "chat": ""
        },
        "source": {
          "custom": "PHB",
          "book": "",
          "page": "",
          "license": "",
          "revision": 1,
          "rules": "2014"
        },
        "activation": {
          "type": "action",
          "condition": "",
          "value": 1
        },
        "duration": {
          "value": "1",
          "units": "minute"
        },
        "target": {
          "affects": {
            "type": "space",
            "count": "1",
            "choice": false
          },
          "template": {
            "units": "",
            "contiguous": false
          }
        },
        "range": {
          "value": "30",
          "units": "ft"
        },
        "uses": {
          "max": "",
          "spent": 0,
          "recovery": []
        },
        "ability": "wis",
        "level": 0,
        "school": "con",
        "materials": {
          "value": "",
          "consumed": false,
          "cost": 0,
          "supply": 0
        },
        "preparation": {
          "mode": "always",
          "prepared": true
        },
        "properties": [
          "vocal",
          "somatic"
        ],
        "activities": {
          "dnd5eactivity000": {
            "_id": "dnd5eactivity000",
            "type": "utility",
            "activation": {
              "type": "action",
              "value": null,
              "override": false
            },
            "consumption": {
              "targets": [],
              "scaling": {
                "allowed": false,
                "max": ""
              },
              "spellSlot": true
            },
            "description": {
              "chatFlavor": ""
            },
            "duration": {
              "units": "inst",
              "concentration": false,
              "override": false
            },
            "effects": [],
            "range": {
              "override": false
            },
            "target": {
              "prompt": true,
              "template": {
                "contiguous": false,
                "units": "ft"
              },
              "affects": {
                "choice": false
              },
              "override": false
            },
            "uses": {
              "spent": 0,
              "max": "",
              "recovery": []
            },
            "roll": {
              "formula": "",
              "name": "",
              "prompt": false,
              "visible": false
            },
            "sort": 0
          }
        },
        "identifier": ""
      },
      "img": "icons/magic/light/orbs-hand-gray.webp",
      "ownership": {
        "default": 0,
        "ZbpZyP5KRR8A9JvZ": 3
      },
      "flags": {
        "dnd5e": {
          "migratedProperties": [
            "vocal",
            "somatic"
          ],
          "persistSourceMigration": true
        }
      },
      "effects": [],
      "_id": "hSxpyIC17CEBP8xD",
      "folder": null,
      "sort": 0,
      "_stats": {
        "compendiumSource": null,
        "duplicateSource": null,
        "coreVersion": "12.331",
        "systemId": "dnd5e",
        "systemVersion": "4.0.1",
        "createdTime": null,
        "modifiedTime": null,
        "lastModifiedBy": null
      },
      "_key": "!actors.items!mjSCqrVYZFiDS9bE.hSxpyIC17CEBP8xD"
    },
    {
      "name": "Видение невидимого",
      "type": "spell",
      "system": {
        "description": {
          "value": "<p>Пока длится заклинание, вы видите &amp;reference[invisible]{невидимых } существ и объекты, как если бы они были видимы, и можете видеть Эфирный план. Эфирные существа и объекты кажутся вам призрачно-полупрозрачными.</p><div id=\"gtx-trans\" style=\"position:absolute;left:-47px;top:-19px\"><div class=\"gtx-trans-icon\"><p> </p></div></div>",
          "chat": ""
        },
        "source": {
          "custom": "PHB",
          "book": "",
          "page": "",
          "license": "",
          "revision": 1,
          "rules": "2014"
        },
        "activation": {
          "type": "action",
          "condition": "",
          "value": 1
        },
        "duration": {
          "value": "1",
          "units": "hour"
        },
        "target": {
          "affects": {
            "type": "self",
            "count": "0",
            "choice": false
          },
          "template": {
            "units": "self",
            "contiguous": false
          }
        },
        "range": {
          "value": "0",
          "units": "self"
        },
        "uses": {
          "max": "",
          "spent": 0,
          "recovery": []
        },
        "ability": "wis",
        "level": 2,
        "school": "div",
        "materials": {
          "value": "щепотка талька и чуть-чуть серебряного порошка",
          "consumed": false,
          "cost": 0,
          "supply": 0
        },
        "preparation": {
          "mode": "innate",
          "prepared": true
        },
        "properties": [
          "vocal",
          "somatic",
          "material"
        ],
        "activities": {
          "dnd5eactivity000": {
            "_id": "dnd5eactivity000",
            "type": "utility",
            "activation": {
              "type": "action",
              "value": null,
              "override": false
            },
            "consumption": {
              "targets": [],
              "scaling": {
                "allowed": false,
                "max": ""
              },
              "spellSlot": true
            },
            "description": {
              "chatFlavor": ""
            },
            "duration": {
              "units": "inst",
              "concentration": false,
              "override": false
            },
            "effects": [],
            "range": {
              "override": false
            },
            "target": {
              "prompt": true,
              "template": {
                "contiguous": false,
                "units": "ft"
              },
              "affects": {
                "choice": false
              },
              "override": false
            },
            "uses": {
              "spent": 0,
              "max": "",
              "recovery": []
            },
            "roll": {
              "formula": "",
              "name": "",
              "prompt": false,
              "visible": false
            },
            "sort": 0
          }
        },
        "identifier": ""
      },
      "img": "icons/magic/control/silhouette-aura-energy.webp",
      "ownership": {
        "default": 0,
        "ZbpZyP5KRR8A9JvZ": 3
      },
      "flags": {
        "dnd5e": {
          "migratedProperties": [
            "vocal",
            "somatic",
            "material"
          ],
          "persistSourceMigration": true
        }
      },
      "effects": [],
      "_id": "YyQNEqDW4TAJdBnP",
      "folder": null,
      "sort": 0,
      "_stats": {
        "compendiumSource": null,
        "duplicateSource": null,
        "coreVersion": "12.331",
        "systemId": "dnd5e",
        "systemVersion": "4.0.1",
        "createdTime": null,
        "modifiedTime": null,
        "lastModifiedBy": null
      },
      "_key": "!actors.items!mjSCqrVYZFiDS9bE.YyQNEqDW4TAJdBnP"
    },
    {
      "name": "Заклинания (Псионика)",
      "type": "feat",
      "system": {
        "description": {
          "value": "<p><span class=\"rd__h rd__h--3\" data-title-index=\"1\">Гитзерай сотворяет одно из следующих заклинаний, используя Мудрость в качестве базовой характеристики и без использования реагентов (СЛ испытания от заклинаний 14):</span></p><p><strong>Неограниченно</strong>: </p><ul class=\"rd__list rd__list-hang-notitle\"><li class=\"rd__li  rd__li-spell\"><p>@UUID[.hSxpyIC17CEBP8xD] (рука невидима), </p></li><li class=\"rd__li  rd__li-spell\"><p>@UUID[.YyQNEqDW4TAJdBnP]</p></li></ul><p><strong>1 в день каждое:</strong> </p><ul class=\"rd__list rd__list-hang-notitle\"><li class=\"rd__li  rd__li-spell\"><p>@UUID[.gQDOlECAwUt2bmtg] (только на себя), </p></li><li class=\"rd__li  rd__li-spell\"><p>@UUID[.GgULV8Nkx736fH8F]</p></li></ul>",
          "chat": ""
        },
        "source": {
          "custom": "MPP",
          "book": "",
          "page": "",
          "license": "",
          "revision": 1,
          "rules": "2014"
        },
        "uses": {
          "max": "",
          "spent": 0,
          "recovery": []
        },
        "type": {
          "value": "",
          "subtype": ""
        },
        "requirements": "",
        "properties": [],
        "activities": {
          "dnd5eactivity000": {
            "_id": "dnd5eactivity000",
            "type": "utility",
            "activation": {
              "type": "action",
              "value": null,
              "condition": "",
              "override": false
            },
            "consumption": {
              "targets": [],
              "scaling": {
                "allowed": false,
                "max": ""
              },
              "spellSlot": true
            },
            "description": {
              "chatFlavor": ""
            },
            "duration": {
              "concentration": false,
              "value": "",
              "units": "",
              "special": "",
              "override": false
            },
            "effects": [],
            "range": {
              "units": "",
              "special": "",
              "override": false
            },
            "target": {
              "template": {
                "count": "",
                "contiguous": false,
                "type": "",
                "size": "",
                "width": "",
                "height": "",
                "units": ""
              },
              "affects": {
                "count": "",
                "type": "",
                "choice": false,
                "special": ""
              },
              "prompt": true,
              "override": false
            },
            "uses": {
              "spent": 0,
              "max": "",
              "recovery": []
            },
            "roll": {
              "formula": "",
              "name": "",
              "prompt": false,
              "visible": false
            },
            "sort": 0
          }
        },
        "identifier": "",
        "enchant": {},
        "prerequisites": {
          "level": null
        }
      },
      "ownership": {
        "default": 0,
        "ZbpZyP5KRR8A9JvZ": 3
      },
      "img": "icons/magic/light/beam-rays-magenta-large.webp",
      "flags": {
        "dnd5e": {
          "persistSourceMigration": true
        }
      },
      "effects": [],
      "_id": "LXQKkK1qNHHrGhLa",
      "folder": null,
      "sort": 0,
      "_stats": {
        "compendiumSource": null,
        "duplicateSource": null,
        "coreVersion": "12.331",
        "systemId": "dnd5e",
        "systemVersion": "4.0.1",
        "createdTime": null,
        "modifiedTime": null,
        "lastModifiedBy": null
      },
      "_key": "!actors.items!mjSCqrVYZFiDS9bE.LXQKkK1qNHHrGhLa"
    },
    {
      "_id": "HGImswKQYb4s33XV",
      "name": "Психическая защита",
      "type": "feat",
      "system": {
        "description": {
          "value": "<p>Пока гитзерай не носит броню и не носит щит, к его КБ добавляется модификатор Мудрости.</p>",
          "chat": ""
        },
        "source": {
          "custom": "MPP",
          "book": "",
          "page": "",
          "license": "",
          "revision": 1,
          "rules": "2014"
        },
        "uses": {
          "max": "",
          "spent": 0,
          "recovery": []
        },
        "type": {
          "value": "monster",
          "subtype": ""
        },
        "requirements": "",
        "properties": [],
        "activities": {
          "dnd5eactivity000": {
            "_id": "dnd5eactivity000",
            "type": "utility",
            "activation": {
              "type": "",
              "value": null,
              "condition": "",
              "override": false
            },
            "consumption": {
              "targets": [],
              "scaling": {
                "allowed": false,
                "max": ""
              },
              "spellSlot": true
            },
            "description": {
              "chatFlavor": ""
            },
            "duration": {
              "concentration": false,
              "value": "",
              "units": "",
              "special": "",
              "override": false
            },
            "effects": [],
            "range": {
              "units": "",
              "special": "",
              "override": false
            },
            "target": {
              "template": {
                "count": "",
                "contiguous": false,
                "type": "",
                "size": "",
                "width": "",
                "height": "",
                "units": ""
              },
              "affects": {
                "count": "",
                "type": "",
                "choice": false,
                "special": ""
              },
              "prompt": true,
              "override": false
            },
            "uses": {
              "spent": 0,
              "max": "",
              "recovery": []
            },
            "roll": {
              "formula": "",
              "name": "",
              "prompt": false,
              "visible": false
            },
            "sort": 0
          }
        },
        "identifier": "",
        "enchant": {},
        "prerequisites": {
          "level": null
        }
      },
      "ownership": {
        "default": 0,
        "ZbpZyP5KRR8A9JvZ": 3,
        "N5s4uI6OpcSYQoF8": 3
      },
      "img": "icons/magic/air/air-burst-spiral-large-yellow.webp",
      "flags": {
        "core": {
          "sourceId": "Actor.hTPGPlwd3c3puRVm.Item.YYOoFtgcuwPnxIiq"
        },
        "dnd5e": {
          "persistSourceMigration": true
        }
      },
      "effects": [],
      "folder": null,
      "sort": 0,
      "_stats": {
        "compendiumSource": "Actor.hTPGPlwd3c3puRVm.Item.YYOoFtgcuwPnxIiq",
        "duplicateSource": null,
        "coreVersion": "12.331",
        "systemId": "dnd5e",
        "systemVersion": "4.0.1",
        "createdTime": null,
        "modifiedTime": null,
        "lastModifiedBy": null
      },
      "_key": "!actors.items!mjSCqrVYZFiDS9bE.HGImswKQYb4s33XV"
    }
  ],
  "effects": [],
  "_stats": {
    "compendiumSource": null,
    "duplicateSource": null,
    "coreVersion": "12.331",
    "systemId": "dnd5e",
    "systemVersion": "4.0.1",
    "createdTime": 1726588007280,
    "modifiedTime": 1726588007280,
    "lastModifiedBy": "T0BtUpu1XTcoijv3"
  },
  "folder": "NNgsZBLj7I2HXvF5",
  "sort": 0,
  "ownership": {
    "default": 0,
    "T0BtUpu1XTcoijv3": 3
  },
  "_key": "!actors!mjSCqrVYZFiDS9bE"
}
