{
  "name": "Гранат",
  "type": "loot",
  "img": "icons/consumables/fruit/pomegranate-ripe-red.webp",
  "system": {
    "description": {
      "value": "<p>Гранат — это сладкий, терпкий фрукт с толстой красной кожурой. Хотя кожица не съедобна, в ней находятся сотни сочных семян, которые можно есть в чистом виде или посыпать ими салаты, каши и другие блюда.</p>",
      "chat": ""
    },
    "source": {
      "custom": "KCoTG",
      "book": "KCoTG",
      "revision": 1,
      "rules": "2014"
    },
    "quantity": 1,
    "weight": {
      "value": 1,
      "units": "lb"
    },
    "price": {
      "value": 2.5,
      "denomination": "gp"
    },
    "rarity": "common",
    "identified": true,
    "unidentified": {
      "description": ""
    },
    "identifier": "granat",
    "container": null,
    "properties": [],
    "type": {
      "value": "",
      "subtype": ""
    }
  },
  "effects": [],
  "flags": {
    "core": {
      "sourceId": "Item.NsfDJdMTP6qbmzzA"
    }
  },
  "_stats": {
    "compendiumSource": "Item.NsfDJdMTP6qbmzzA",
    "duplicateSource": null,
    "coreVersion": "12.331",
    "systemId": "dnd5e",
    "systemVersion": "4.0.1",
    "createdTime": 1726661592018,
    "modifiedTime": 1739365143596,
    "lastModifiedBy": "rIPjwHOPF73FMTHt"
  },
  "_id": "CUvay6HNa6vlT9Af",
  "folder": "ZHvijmEqihjAOA9i",
  "sort": 112500,
  "ownership": {
    "default": 0,
    "UkvoHT2ggFpbOAml": 3
  },
  "_key": "!items!CUvay6HNa6vlT9Af"
}
