{
  "name": "Мак",
  "type": "loot",
  "img": "icons/commodities/flowers/lotus-pink.webp",
  "system": {
    "description": {
      "value": "<p>Хлебный мак — декоративное растение, часто встречающееся в садах. Его выращивают ради его семян, масла и лекарственных свойств. В сочетании с крепким алкоголем его можно использовать как мощное обезболивающее средство.</p>",
      "chat": ""
    },
    "source": {
      "custom": "KCoTG",
      "book": "KCoTG",
      "revision": 1,
      "rules": "2014"
    },
    "quantity": 1,
    "weight": {
      "value": 0.1,
      "units": "lb"
    },
    "price": {
      "value": 1.2,
      "denomination": "gp"
    },
    "rarity": "",
    "identified": true,
    "unidentified": {
      "description": ""
    },
    "identifier": "mak",
    "container": null,
    "properties": [],
    "type": {
      "value": "",
      "subtype": ""
    }
  },
  "effects": [],
  "flags": {
    "core": {
      "sourceId": "Item.D0DTmD8ULtkht4ah"
    }
  },
  "_stats": {
    "compendiumSource": "Item.D0DTmD8ULtkht4ah",
    "duplicateSource": null,
    "coreVersion": "12.331",
    "systemId": "dnd5e",
    "systemVersion": "4.0.1",
    "createdTime": 1726661592018,
    "modifiedTime": 1739365661222,
    "lastModifiedBy": "rIPjwHOPF73FMTHt"
  },
  "_id": "L0FR10ULxZfnYcY5",
  "folder": "ZHvijmEqihjAOA9i",
  "sort": 6100000,
  "ownership": {
    "default": 0,
    "UkvoHT2ggFpbOAml": 3
  },
  "_key": "!items!L0FR10ULxZfnYcY5"
}
