{
  "_id": "9Gs0F0yHIuSL5Ffz",
  "name": "Амулет благочестия +2 / +2 Amulet of the Devout",
  "type": "equipment",
  "img": "modules/laaru-dnd5-hw/assets/images/pic/Amulet%20of%20the%20Devout.webp",
  "effects": [
    {
      "_id": "F3Y6h4F1rUz1OIZU",
      "changes": [
        {
          "key": "system.bonuses.spell.attack",
          "mode": 2,
          "value": "2",
          "priority": 20
        },
        {
          "key": "system.bonuses.spell.dc",
          "mode": 2,
          "value": "2",
          "priority": 20
        }
      ],
      "disabled": false,
      "duration": {
        "startTime": null,
        "seconds": null,
        "combat": null,
        "rounds": null,
        "turns": null,
        "startRound": null,
        "startTurn": null
      },
      "origin": "Item.9Gs0F0yHIuSL5Ffz",
      "transfer": true,
      "flags": {
        "dae": {
          "selfTarget": false,
          "stackable": "none",
          "durationExpression": "",
          "specialDuration": [],
          "transfer": true
        },
        "core": {
          "statusId": ""
        }
      },
      "tint": "#ffffff",
      "name": "Бонус от амулета",
      "description": "",
      "statuses": [],
      "_stats": {
        "compendiumSource": null,
        "duplicateSource": null,
        "coreVersion": "12.331",
        "systemId": "dnd5e",
        "systemVersion": "4.2.2",
        "createdTime": null,
        "modifiedTime": null,
        "lastModifiedBy": null
      },
      "img": "modules/laaru-dnd5-hw/assets/images/pic/Amulet%20of%20the%20Devout.webp",
      "type": "base",
      "system": {},
      "sort": 0,
      "_key": "!items.effects!9Gs0F0yHIuSL5Ffz.F3Y6h4F1rUz1OIZU"
    }
  ],
  "flags": {
    "srd5e": {
      "page": "",
      "source": "TCE",
      "hash": "%2b2%20amulet%20of%20the%20devout_tce"
    },
    "scene-packer": {
      "hash": "eee16a90a155fc3b9c9811be70ba98f1fd1c198f",
      "sourceId": "Item.9Gs0F0yHIuSL5Ffz"
    },
    "cf": {
      "id": "temp_w72fypjwmfj",
      "path": "tasha",
      "color": "#000000"
    },
    "betterRolls5e": {
      "quickDesc": {
        "value": true,
        "altValue": true
      },
      "quickProperties": {
        "value": true,
        "altValue": true
      },
      "quickOther": {
        "value": true,
        "altValue": true
      },
      "quickFlavor": {
        "value": true,
        "altValue": true
      },
      "quickCharges": {
        "value": {
          "quantity": false
        },
        "altValue": {
          "quantity": false
        }
      }
    },
    "core": {
      "sourceId": "Compendium.laaru-dnd5-hw.items.9Gs0F0yHIuSL5Ffz"
    },
    "babele": {
      "hasTranslation": true,
      "originalName": "+2 Amulet of the Devout",
      "translated": true
    }
  },
  "system": {
    "description": {
      "value": "<p><em>Чудесный предмет, требуется настроенность жрецом или паладином</em></p>\n<p>На этом амулете изображен символ божества в виде инкрустированных драгоценных камней или металлов. Пока вы носите этот священный символ, вы получаете бонус <strong>+2</strong> к броскам атаки заклинаниями и к СЛ испытаний ваших заклинаний.</p>\n<p>Пока вы носите этот амулет, вы можете использовать особенность <em>Проведение энергии</em>, не потратив заряд использований. Это свойство не может быть использовано вновь до следующего рассвета.</p>",
      "chat": ""
    },
    "source": {
      "custom": "TCE",
      "revision": 1,
      "book": "TCE",
      "rules": "2014"
    },
    "quantity": 1,
    "weight": {
      "value": 1,
      "units": "lb"
    },
    "price": {
      "value": 0,
      "denomination": "gp"
    },
    "attunement": "required",
    "equipped": true,
    "rarity": "rare",
    "identified": true,
    "cover": null,
    "crewed": false,
    "uses": {
      "max": "",
      "spent": 0,
      "recovery": []
    },
    "armor": {
      "value": null,
      "dex": null,
      "magicalBonus": null
    },
    "hp": {
      "value": 0,
      "max": 0,
      "dt": null,
      "conditions": ""
    },
    "speed": {
      "value": null,
      "conditions": ""
    },
    "strength": null,
    "proficient": 1,
    "unidentified": {
      "description": ""
    },
    "type": {
      "value": "trinket",
      "baseItem": ""
    },
    "activities": {},
    "identifier": "amulet-blagochestiya-2--2-amulet-of-the-devout",
    "container": null,
    "attuned": true,
    "properties": [
      "mgc"
    ]
  },
  "_stats": {
    "compendiumSource": "Compendium.laaru-dnd5-hw.items.9Gs0F0yHIuSL5Ffz",
    "duplicateSource": null,
    "coreVersion": "12.331",
    "systemId": "dnd5e",
    "systemVersion": "4.2.2",
    "createdTime": 1739354874978,
    "modifiedTime": 1739354874978,
    "lastModifiedBy": "rIPjwHOPF73FMTHt"
  },
  "folder": "Q7xJMCFr1vXrTDNd",
  "sort": 0,
  "ownership": {
    "default": 0,
    "rIPjwHOPF73FMTHt": 3
  },
  "_key": "!items!9Gs0F0yHIuSL5Ffz"
}
