{
  "_id": "ivswg1N0SjLkvL8U",
  "name": "Планарный амулет / Amulet of the Planes",
  "type": "equipment",
  "img": "modules/laaru-dnd5-hw/assets/images/pic/Amulet%20of%20the%20Planes.webp",
  "effects": [],
  "flags": {
    "srd5e": {
      "page": "",
      "source": "DMG",
      "hash": "amulet%20of%20the%20planes_dmg"
    },
    "core": {
      "sourceId": "Compendium.laaru-dnd5-hw.items.ivswg1N0SjLkvL8U"
    },
    "babele": {
      "hasTranslation": true,
      "originalName": "Amulet of the Planes",
      "translated": true
    }
  },
  "system": {
    "description": {
      "value": "<p>Пока вы носите этот амулет, вы можете использовать действие, чтобы назвать знакомое вам место на другом плане бытия. Затем пройдите проверку Интеллекта со СЛ 15. При успехе вы сотворяете заклинание @Compendium[laaru-dnd5-hw.spells.gxAncMbwLb3QJayh]{Планарный переход}. При провале вы и каждое существо и объект в пределах 15 футов от вас перемещаетесь в случайно выбранное место. Бросьте [[/r d100]]. Если выпало от 1 до 60, вы перемещаетесь в случайное место на названном вами плане. Если выпало от 61 до 100, вы перемещаетесь на случайно выбранный план бытия.</p>",
      "chat": ""
    },
    "source": {
      "custom": "DMG",
      "revision": 1,
      "book": "DMG",
      "rules": "2014"
    },
    "quantity": 1,
    "weight": {
      "value": 1,
      "units": "lb"
    },
    "price": {
      "value": 0,
      "denomination": "gp"
    },
    "attunement": "required",
    "equipped": true,
    "rarity": "veryRare",
    "identified": true,
    "cover": null,
    "uses": {
      "max": "",
      "spent": 0,
      "recovery": []
    },
    "armor": {
      "value": null,
      "dex": null,
      "magicalBonus": null
    },
    "hp": {
      "value": 0,
      "max": 0,
      "dt": null,
      "conditions": ""
    },
    "speed": {
      "value": null,
      "conditions": ""
    },
    "strength": 0,
    "proficient": 1,
    "crewed": false,
    "unidentified": {
      "description": ""
    },
    "type": {
      "value": "",
      "baseItem": ""
    },
    "activities": {},
    "identifier": "planarnyj-amulet--amulet-of-the-planes",
    "container": null,
    "attuned": false,
    "properties": []
  },
  "_stats": {
    "compendiumSource": "Compendium.laaru-dnd5-hw.items.ivswg1N0SjLkvL8U",
    "duplicateSource": null,
    "coreVersion": "12.331",
    "systemId": "dnd5e",
    "systemVersion": "4.2.2",
    "createdTime": 1739354874978,
    "modifiedTime": 1739354874978,
    "lastModifiedBy": "rIPjwHOPF73FMTHt"
  },
  "folder": "Q7xJMCFr1vXrTDNd",
  "sort": 0,
  "ownership": {
    "default": 0,
    "rIPjwHOPF73FMTHt": 3
  },
  "_key": "!items!ivswg1N0SjLkvL8U"
}
