{
  "name": "Предыстория чужеземца",
  "img": "icons/sundries/documents/document-letter-blue.webp",
  "description": "Baldur's Gate Descent into Avernus",
  "results": [
    {
      "_id": "VocT1sr0NjNuZJFQ",
      "type": "text",
      "text": "Кто-то украл что-то ценное у вашего народа. Вы выследили вора до городских ворот, однако найти его в городской толчее куда труднее, чем в дикой глуши. Вы не знаете, куда идти дальше, но ваш народ рассчитывает на вас.",
      "weight": 1,
      "range": [
        1,
        1
      ],
      "drawn": false,
      "flags": {},
      "img": "icons/svg/d20-black.svg",
      "documentCollection": "",
      "documentId": null,
      "_key": "!tables.results!rmsCWvbPWiDRgqHY.VocT1sr0NjNuZJFQ"
    },
    {
      "_id": "dMfg6rheWHFKiA6i",
      "type": "text",
      "text": "Вас всегда привлекали блеск и роскошь городской жизни, так непохожие на нудную повседневность у вас на родине. Теперь вы тут, готовы оставить свой след в мире, но не знаете, с чего начать.",
      "weight": 1,
      "range": [
        2,
        2
      ],
      "drawn": false,
      "flags": {},
      "img": "icons/svg/d20-black.svg",
      "documentCollection": "",
      "documentId": null,
      "_key": "!tables.results!rmsCWvbPWiDRgqHY.dMfg6rheWHFKiA6i"
    },
    {
      "_id": "H1Mv5irMOCuT0I5Q",
      "type": "text",
      "text": "Война, эпидемия, голод или набеги чудовищ разорили вашу родину, и вам пришлось спасаться бегством. Вы толком не знаете, как много из вашего народа уцелело и где их искать. Вы одни или в сопровождении горстки таких же потерянных беженцев. Вам надо разобраться в новой жизни, которой вы никогда не желали.",
      "weight": 1,
      "range": [
        3,
        3
      ],
      "drawn": false,
      "flags": {},
      "img": "icons/svg/d20-black.svg",
      "documentCollection": "",
      "documentId": null,
      "_key": "!tables.results!rmsCWvbPWiDRgqHY.H1Mv5irMOCuT0I5Q"
    },
    {
      "_id": "cY3huYMU9hZNGSR1",
      "type": "text",
      "text": "Вас похитили и увезли далеко от дома. Рыцари Единорога освободили вас и привезли сюда, но теперь вы сами по себе.",
      "weight": 1,
      "range": [
        4,
        4
      ],
      "drawn": false,
      "flags": {},
      "img": "icons/svg/d20-black.svg",
      "documentCollection": "",
      "documentId": null,
      "_key": "!tables.results!rmsCWvbPWiDRgqHY.cY3huYMU9hZNGSR1"
    },
    {
      "_id": "Yn35pS5sueSLiwlt",
      "type": "text",
      "text": "Вас изгнали за нарушение пустякового запрета. За такое вроде бы мелкое прегрешение вы потеряли семью, друзей и родину в один миг. Вам не осталось ничего, кроме как пробиваться самому.",
      "weight": 1,
      "range": [
        5,
        5
      ],
      "drawn": false,
      "flags": {},
      "img": "icons/svg/d20-black.svg",
      "documentCollection": "",
      "documentId": null,
      "_key": "!tables.results!rmsCWvbPWiDRgqHY.Yn35pS5sueSLiwlt"
    },
    {
      "_id": "RMef17773Jilrzi5",
      "type": "text",
      "text": "Однажды торговец привёз к вам на родину нечто удивительное—заводную машину Гонда, блестящую золотую ткань, дрессированную говорящую птицу или какое-то другое чудо. Он сказал, что купил это во Вратах Балдура. Вы хотите увидеть источник этих чудес — и, может быть, научиться их создавать.",
      "weight": 1,
      "range": [
        6,
        6
      ],
      "drawn": false,
      "flags": {},
      "img": "icons/svg/d20-black.svg",
      "documentCollection": "",
      "documentId": null,
      "_key": "!tables.results!rmsCWvbPWiDRgqHY.RMef17773Jilrzi5"
    }
  ],
  "formula": "1d10",
  "replacement": true,
  "displayRoll": true,
  "flags": {
    "core": {
      "sourceId": "Compendium.laaru-dnd5-hw.tables.ETvFaRImdgkeAl8k"
    }
  },
  "ownership": {
    "default": 0,
    "ekSJaSkR4p1sowmM": 3
  },
  "_stats": {
    "systemId": "dnd5e",
    "systemVersion": "2.1.5",
    "coreVersion": "12.331",
    "createdTime": 1671631652449,
    "modifiedTime": 1682000359080,
    "lastModifiedBy": "WiAz8G0ybh7NpFaK",
    "compendiumSource": "Compendium.laaru-dnd5-hw.tables.ETvFaRImdgkeAl8k",
    "duplicateSource": null
  },
  "folder": null,
  "sort": 0,
  "_id": "rmsCWvbPWiDRgqHY",
  "_key": "!tables!rmsCWvbPWiDRgqHY"
}
