{
  "name": "Латный доспех падшего / Plate Armor of the Fallen",
  "type": "equipment",
  "system": {
    "description": {
      "value": "<p>Пока вы носите эту броню, вы можете использовать его для сотворения заклинаний @Compendium[laaru-dnd5-hw.spells.mx2A40HWjlyslxKm]{Разговор с мёртвыми} или @Compendium[laaru-dnd5-hw.spells.OQEPzL4bMfxpUjwi]{Оживление мертвецов}.</p><p>Если броня использовалась для сотворения заклинания таким образом, она не может использоваться для сотворения ни одного из заклинаний до следующего рассвета.</p><p>Ваша душа поддерживает эту броню. Если вы умрете, будучи настроенным на броню, то броня будет разрушена.</p><p>Состоит из кованых металлических пластин, сцепленных друг с другом и покрывающих всё тело. В латный доспех входят рукавицы, тяжёлые кожаные сапоги, шлем с забралом и толстый поддоспешник. Пряжки и ремни позволяют распределить вес по всему телу.</p>",
      "chat": ""
    },
    "source": {
      "custom": "BMT",
      "book": "BMT",
      "page": "",
      "license": "",
      "revision": 1,
      "rules": "2014"
    },
    "quantity": 1,
    "weight": {
      "value": 65,
      "units": "lb"
    },
    "price": {
      "value": 0,
      "denomination": "gp"
    },
    "attunement": "required",
    "equipped": true,
    "rarity": "uncommon",
    "identified": true,
    "cover": null,
    "crewed": false,
    "uses": {
      "max": "",
      "spent": 0,
      "recovery": []
    },
    "armor": {
      "value": 18,
      "dex": 0,
      "magicalBonus": null
    },
    "hp": {
      "value": 0,
      "max": 0,
      "dt": null,
      "conditions": ""
    },
    "speed": {
      "value": null,
      "conditions": ""
    },
    "strength": 15,
    "proficient": null,
    "unidentified": {
      "description": ""
    },
    "type": {
      "value": "heavy",
      "baseItem": "plate"
    },
    "container": null,
    "properties": [
      "stealthDisadvantage"
    ],
    "activities": {},
    "identifier": "latnyj-dospeh-padshego--plate-armor-of-the-fallen",
    "attuned": false
  },
  "img": "icons/equipment/chest/breastplate-collared-steel.webp",
  "flags": {
    "core": {},
    "dnd5e": {
      "migratedProperties": [
        "stealthDisadvantage"
      ]
    }
  },
  "effects": [],
  "_stats": {
    "compendiumSource": null,
    "duplicateSource": null,
    "coreVersion": "12.331",
    "systemId": "dnd5e",
    "systemVersion": "4.2.2",
    "createdTime": 1739354874978,
    "modifiedTime": 1739354874978,
    "lastModifiedBy": "rIPjwHOPF73FMTHt"
  },
  "_id": "IwDUn1SMhQ6mnXHt",
  "folder": "ojQSTbdzWZJCR4aN",
  "sort": 0,
  "ownership": {
    "default": 0,
    "rIPjwHOPF73FMTHt": 3
  },
  "_key": "!items!IwDUn1SMhQ6mnXHt"
}
