{
  "name": "Хронолометр / Chronolometer",
  "type": "equipment",
  "system": {
    "description": {
      "value": "<p><em>Чудесный предмет (требуется настроенность)</em></p><p>Будучи настроенным на это устройство, вы получаете бонус +1 к испытаниям Интеллекта. Впервые, когда вы настраиваетесь на хронолометр, вы выбираете один язык, который вы не знаете. Впоследствии вы узнаете этот язык, настроившись на предмет.</p><p><strong>Вор времени</strong>. В начале своего хода сделайте бросок [[/r d6]] (никаких действий не требуется). При выпадении «1-3» вы замедляете время, получая дополнительное Действие в этом ходу и удваивая свою скорость до конца хода. При выпадении «4-6» вы отправляетесь вперед во времени, чтобы предупредить себя о том, что должно произойти. В следующий раз, когда вы проваливаете испытание, проверку характеристики или промахнётесь броском атаки, вы можете повторить бросок и использовать любой результат. Как только вы используете это свойство хронолометра, оно не может быть использовано снова до следующего рассвета.</p><p><strong>Обмен судьбами</strong>. Когда существо, которое вы видите в пределах 30 футов от вас, получает урон, вы можете @Compendium[laaru-dnd5-hw.actions.mMwkUE20bEfKeetq]{ответным действием}, даровать этому существу дополнительное Действие. Существо может использовать это Действие в свой ход, или использовать его незамедлительно, даже если сейчас не его ход. Как только вы используете это свойство хронолометра, оно не может быть использовано снова до следующего рассвета.</p><p><strong>Часть целого</strong>. Пока этот компонент не установлен в Планетарий странника, его магия может функционировать с перебоями или с непредсказуемыми побочными эффектами, как решит Мастер.</p>",
      "chat": ""
    },
    "source": {
      "custom": "AI",
      "book": "AI",
      "page": "",
      "license": "",
      "revision": 1,
      "rules": "2014"
    },
    "quantity": 1,
    "weight": {
      "value": 0,
      "units": "lb"
    },
    "price": {
      "value": 0,
      "denomination": "gp"
    },
    "attunement": "required",
    "equipped": true,
    "rarity": "veryRare",
    "identified": true,
    "cover": null,
    "crewed": false,
    "uses": {
      "max": "",
      "spent": 0,
      "recovery": []
    },
    "armor": {
      "value": null,
      "dex": null,
      "magicalBonus": null
    },
    "hp": {
      "value": 0,
      "max": 0,
      "dt": null,
      "conditions": ""
    },
    "speed": {
      "value": null,
      "conditions": ""
    },
    "strength": null,
    "proficient": null,
    "unidentified": {
      "description": ""
    },
    "type": {
      "value": "trinket",
      "baseItem": ""
    },
    "activities": {},
    "identifier": "hronolometr--chronolometer",
    "container": null,
    "attuned": false,
    "properties": []
  },
  "img": "icons/magic/time/clock-spinning-gold-pink.webp",
  "flags": {
    "core": {
      "sourceId": "Item.Lj50dmBjUSNmMw0j"
    }
  },
  "effects": [
    {
      "changes": [
        {
          "key": "system.bonuses.abilities.save",
          "mode": 2,
          "value": "+1",
          "priority": null
        }
      ],
      "disabled": false,
      "duration": {
        "startTime": null,
        "seconds": null,
        "rounds": null,
        "turns": null,
        "startRound": null,
        "startTurn": null,
        "combat": null
      },
      "origin": null,
      "tint": "#ffffff",
      "transfer": true,
      "flags": {},
      "_id": "IurWonucTHAeIeCC",
      "name": "Бонус к испытанию",
      "description": "",
      "statuses": [],
      "_stats": {
        "compendiumSource": null,
        "duplicateSource": null,
        "coreVersion": "12.331",
        "systemId": "dnd5e",
        "systemVersion": "4.2.2",
        "createdTime": null,
        "modifiedTime": null,
        "lastModifiedBy": null
      },
      "img": "icons/magic/time/clock-spinning-gold-pink.webp",
      "type": "base",
      "system": {},
      "sort": 0,
      "_key": "!items.effects!Lj50dmBjUSNmMw0j.IurWonucTHAeIeCC"
    }
  ],
  "_id": "Lj50dmBjUSNmMw0j",
  "_stats": {
    "compendiumSource": "Item.Lj50dmBjUSNmMw0j",
    "duplicateSource": null,
    "coreVersion": "12.331",
    "systemId": "dnd5e",
    "systemVersion": "4.2.2",
    "createdTime": 1739354874978,
    "modifiedTime": 1739354874978,
    "lastModifiedBy": "rIPjwHOPF73FMTHt"
  },
  "folder": null,
  "sort": 0,
  "ownership": {
    "default": 0,
    "rIPjwHOPF73FMTHt": 3
  },
  "_key": "!items!Lj50dmBjUSNmMw0j"
}
